{"updated": "2023-11-01T13:48:36.717428+00:00", "teams": {"ATL": {"TEAM_ID": 1610612737, "TEAM_NAME": "Atlanta Hawks", "GP": 82, "W": 44, "L": 38, "MIN": 3946.0, "OFF_RATING": 105.1, "DEF_RATING": 105.8, "NET_RATING": -0.7, "AST_PCT": 0.607, "AST_TO": 1.61, "AST_RATIO": 17.7, "OREB_PCT": 0.274, "DREB_PCT": 0.71, "REB_PCT": 0.494, "TM_TOV_PCT": 0.151, "EFG_PCT": 0.501, "TS_PCT": 0.542, "PACE": 90.22, "PACE_PER40": 75.18, "POSS": 7410}, "BOS": {"TEAM_ID": 1610612738, "TEAM_NAME": "Boston Celtics", "GP": 82, "W": 56, "L": 26, "MIN": 3956.0, "OFF_RATING": 105.5, "DEF_RATING": 99.8, "NET_RATING": 5.7, "AST_PCT": 0.635, "AST_TO": 1.61, "AST_RATIO": 18.8, "OREB_PCT": 0.257, "DREB_PCT": 0.709, "REB_PCT": 0.497, "TM_TOV_PCT": 0.159, "EFG_PCT": 0.519, "TS_PCT": 0.561, "PACE": 90.92, "PACE_PER40": 75.77, "POSS": 7500}, "CHA": {"TEAM_ID": 1610612766, "TEAM_NAME": "Charlotte Bobcats", "GP": 82, "W": 34, "L": 48, "MIN": 3961.0, "OFF_RATING": 102.8, "DEF_RATING": 107.0, "NET_RATING": -4.2, "AST_PCT": 0.601, "AST_TO": 1.45, "AST_RATIO": 16.9, "OREB_PCT": 0.298, "DREB_PCT": 0.705, "REB_PCT": 0.502, "TM_TOV_PCT": 0.16, "EFG_PCT": 0.482, "TS_PCT": 0.528, "PACE": 90.3, "PACE_PER40": 75.25, "POSS": 7444}, "CHI": {"TEAM_ID": 1610612741, "TEAM_NAME": "Chicago Bulls", "GP": 82, "W": 62, "L": 20, "MIN": 3966.0, "OFF_RATING": 107.2, "DEF_RATING": 99.5, "NET_RATING": 7.8, "AST_PCT": 0.601, "AST_TO": 1.57, "AST_RATIO": 17.3, "OREB_PCT": 0.332, "DREB_PCT": 0.717, "REB_PCT": 0.528, "TM_TOV_PCT": 0.154, "EFG_PCT": 0.501, "TS_PCT": 0.541, "PACE": 91.2, "PACE_PER40": 76.0, "POSS": 7542}, "CLE": {"TEAM_ID": 1610612739, "TEAM_NAME": "Cleveland Cavaliers", "GP": 82, "W": 19, "L": 63, "MIN": 3951.0, "OFF_RATING": 101.5, "DEF_RATING": 110.9, "NET_RATING": -9.5, "AST_PCT": 0.596, "AST_TO": 1.48, "AST_RATIO": 16.4, "OREB_PCT": 0.283, "DREB_PCT": 0.699, "REB_PCT": 0.485, "TM_TOV_PCT": 0.151, "EFG_PCT": 0.472, "TS_PCT": 0.518, "PACE": 93.76, "PACE_PER40": 78.14, "POSS": 7715}, "DAL": {"TEAM_ID": 1610612742, "TEAM_NAME": "Dallas Mavericks", "GP": 82, "W": 57, "L": 25, "MIN": 3941.0, "OFF_RATING": 108.4, "DEF_RATING": 104.1, "NET_RATING": 4.4, "AST_PCT": 0.637, "AST_TO": 1.71, "AST_RATIO": 18.7, "OREB_PCT": 0.278, "DREB_PCT": 0.713, "REB_PCT": 0.504, "TM_TOV_PCT": 0.151, "EFG_PCT": 0.525, "TS_PCT": 0.565, "PACE": 92.24, "PACE_PER40": 76.86, "POSS": 7581}, "DEN": {"TEAM_ID": 1610612743, "TEAM_NAME": "Denver Nuggets", "GP": 82, "W": 50, "L": 32, "MIN": 3941.0, "OFF_RATING": 111.7, "DEF_RATING": 106.8, "NET_RATING": 4.9, "AST_PCT": 0.576, "AST_TO": 1.57, "AST_RATIO": 17.0, "OREB_PCT": 0.283, "DREB_PCT": 0.716, "REB_PCT": 0.506, "TM_TOV_PCT": 0.147, "EFG_PCT": 0.526, "TS_PCT": 0.574, "PACE": 96.06, "PACE_PER40": 80.05, "POSS": 7888}, "DET": {"TEAM_ID": 1610612765, "TEAM_NAME": "Detroit Pistons", "GP": 82, "W": 30, "L": 52, "MIN": 3976.0, "OFF_RATING": 107.0, "DEF_RATING": 110.7, "NET_RATING": -3.7, "AST_PCT": 0.566, "AST_TO": 1.62, "AST_RATIO": 16.8, "OREB_PCT": 0.317, "DREB_PCT": 0.681, "REB_PCT": 0.491, "TM_TOV_PCT": 0.144, "EFG_PCT": 0.495, "TS_PCT": 0.533, "PACE": 89.79, "PACE_PER40": 74.83, "POSS": 7428}, "GSW": {"TEAM_ID": 1610612744, "TEAM_NAME": "Golden State Warriors", "GP": 82, "W": 36, "L": 46, "MIN": 3966.0, "OFF_RATING": 107.1, "DEF_RATING": 109.4, "NET_RATING": -2.3, "AST_PCT": 0.568, "AST_TO": 1.54, "AST_RATIO": 17.0, "OREB_PCT": 0.3, "DREB_PCT": 0.659, "REB_PCT": 0.476, "TM_TOV_PCT": 0.151, "EFG_PCT": 0.51, "TS_PCT": 0.544, "PACE": 95.85, "PACE_PER40": 79.88, "POSS": 7916}, "HOU": {"TEAM_ID": 1610612745, "TEAM_NAME": "Houston Rockets", "GP": 82, "W": 43, "L": 39, "MIN": 3976.0, "OFF_RATING": 110.2, "DEF_RATING": 107.9, "NET_RATING": 2.3, "AST_PCT": 0.617, "AST_TO": 1.76, "AST_RATIO": 17.8, "OREB_PCT": 0.315, "DREB_PCT": 0.69, "REB_PCT": 0.501, "TM_TOV_PCT": 0.141, "EFG_PCT": 0.503, "TS_PCT": 0.55, "PACE": 95.14, "PACE_PER40": 79.28, "POSS": 7880}, "IND": {"TEAM_ID": 1610612754, "TEAM_NAME": "Indiana Pacers", "GP": 82, "W": 37, "L": 45, "MIN": 3956.0, "OFF_RATING": 104.1, "DEF_RATING": 105.0, "NET_RATING": -0.9, "AST_PCT": 0.536, "AST_TO": 1.28, "AST_RATIO": 15.2, "OREB_PCT": 0.297, "DREB_PCT": 0.703, "REB_PCT": 0.501, "TM_TOV_PCT": 0.16, "EFG_PCT": 0.486, "TS_PCT": 0.533, "PACE": 95.5, "PACE_PER40": 79.59, "POSS": 7864}, "LAC": {"TEAM_ID": 1610612746, "TEAM_NAME": "Los Angeles Clippers", "GP": 82, "W": 32, "L": 50, "MIN": 3971.0, "OFF_RATING": 104.8, "DEF_RATING": 108.0, "NET_RATING": -3.2, "AST_PCT": 0.601, "AST_TO": 1.35, "AST_RATIO": 16.9, "OREB_PCT": 0.33, "DREB_PCT": 0.692, "REB_PCT": 0.511, "TM_TOV_PCT": 0.174, "EFG_PCT": 0.496, "TS_PCT": 0.535, "PACE": 93.35, "PACE_PER40": 77.79, "POSS": 7718}, "LAL": {"TEAM_ID": 1610612747, "TEAM_NAME": "Los Angeles Lakers", "GP": 82, "W": 57, "L": 25, "MIN": 3966.0, "OFF_RATING": 109.6, "DEF_RATING": 103.3, "NET_RATING": 6.3, "AST_PCT": 0.576, "AST_TO": 1.68, "AST_RATIO": 17.0, "OREB_PCT": 0.325, "DREB_PCT": 0.692, "REB_PCT": 0.513, "TM_TOV_PCT": 0.141, "EFG_PCT": 0.502, "TS_PCT": 0.545, "PACE": 91.78, "PACE_PER40": 76.48, "POSS": 7594}, "MEM": {"TEAM_ID": 1610612763, "TEAM_NAME": "Memphis Grizzlies", "GP": 82, "W": 46, "L": 36, "MIN": 3976.0, "OFF_RATING": 107.0, "DEF_RATING": 104.5, "NET_RATING": 2.5, "AST_PCT": 0.528, "AST_TO": 1.48, "AST_RATIO": 16.0, "OREB_PCT": 0.333, "DREB_PCT": 0.682, "REB_PCT": 0.505, "TM_TOV_PCT": 0.15, "EFG_PCT": 0.493, "TS_PCT": 0.534, "PACE": 92.42, "PACE_PER40": 77.02, "POSS": 7656}, "MIA": {"TEAM_ID": 1610612748, "TEAM_NAME": "Miami Heat", "GP": 82, "W": 58, "L": 24, "MIN": 3956.0, "OFF_RATING": 110.6, "DEF_RATING": 102.9, "NET_RATING": 7.8, "AST_PCT": 0.541, "AST_TO": 1.44, "AST_RATIO": 16.1, "OREB_PCT": 0.287, "DREB_PCT": 0.715, "REB_PCT": 0.514, "TM_TOV_PCT": 0.151, "EFG_PCT": 0.524, "TS_PCT": 0.573, "PACE": 91.63, "PACE_PER40": 76.36, "POSS": 7564}, "MIL": {"TEAM_ID": 1610612749, "TEAM_NAME": "Milwaukee Bucks", "GP": 82, "W": 35, "L": 47, "MIN": 3966.0, "OFF_RATING": 100.8, "DEF_RATING": 101.5, "NET_RATING": -0.8, "AST_PCT": 0.549, "AST_TO": 1.4, "AST_RATIO": 15.3, "OREB_PCT": 0.287, "DREB_PCT": 0.71, "REB_PCT": 0.492, "TM_TOV_PCT": 0.148, "EFG_PCT": 0.467, "TS_PCT": 0.511, "PACE": 90.57, "PACE_PER40": 75.47, "POSS": 7477}, "MIN": {"TEAM_ID": 1610612750, "TEAM_NAME": "Minnesota Timberwolves", "GP": 82, "W": 17, "L": 65, "MIN": 3956.0, "OFF_RATING": 103.2, "DEF_RATING": 109.9, "NET_RATING": -6.7, "AST_PCT": 0.534, "AST_TO": 1.18, "AST_RATIO": 15.0, "OREB_PCT": 0.336, "DREB_PCT": 0.698, "REB_PCT": 0.512, "TM_TOV_PCT": 0.174, "EFG_PCT": 0.483, "TS_PCT": 0.526, "PACE": 97.49, "PACE_PER40": 81.24, "POSS": 8034}, "BKN": {"TEAM_ID": 1610612751, "TEAM_NAME": "New Jersey Nets", "GP": 82, "W": 24, "L": 58, "MIN": 4001.0, "OFF_RATING": 102.1, "DEF_RATING": 108.9, "NET_RATING": -6.8, "AST_PCT": 0.59, "AST_TO": 1.5, "AST_RATIO": 16.6, "OREB_PCT": 0.304, "DREB_PCT": 0.7, "REB_PCT": 0.497, "TM_TOV_PCT": 0.152, "EFG_PCT": 0.474, "TS_PCT": 0.517, "PACE": 90.7, "PACE_PER40": 75.59, "POSS": 7563}, "NOP": {"TEAM_ID": 1610612740, "TEAM_NAME": "New Orleans Hornets", "GP": 82, "W": 46, "L": 36, "MIN": 3966.0, "OFF_RATING": 105.4, "DEF_RATING": 104.4, "NET_RATING": 1.0, "AST_PCT": 0.574, "AST_TO": 1.58, "AST_RATIO": 16.8, "OREB_PCT": 0.289, "DREB_PCT": 0.721, "REB_PCT": 0.503, "TM_TOV_PCT": 0.145, "EFG_PCT": 0.493, "TS_PCT": 0.537, "PACE": 89.4, "PACE_PER40": 74.5, "POSS": 7387}, "NYK": {"TEAM_ID": 1610612752, "TEAM_NAME": "New York Knicks", "GP": 82, "W": 42, "L": 40, "MIN": 3956.0, "OFF_RATING": 109.9, "DEF_RATING": 109.0, "NET_RATING": 1.0, "AST_PCT": 0.56, "AST_TO": 1.56, "AST_RATIO": 16.4, "OREB_PCT": 0.273, "DREB_PCT": 0.676, "REB_PCT": 0.473, "TM_TOV_PCT": 0.141, "EFG_PCT": 0.513, "TS_PCT": 0.561, "PACE": 96.47, "PACE_PER40": 80.39, "POSS": 7945}, "OKC": {"TEAM_ID": 1610612760, "TEAM_NAME": "Oklahoma City Thunder", "GP": 82, "W": 55, "L": 27, "MIN": 4001.0, "OFF_RATING": 109.9, "DEF_RATING": 105.9, "NET_RATING": 3.9, "AST_PCT": 0.545, "AST_TO": 1.45, "AST_RATIO": 15.8, "OREB_PCT": 0.306, "DREB_PCT": 0.697, "REB_PCT": 0.507, "TM_TOV_PCT": 0.148, "EFG_PCT": 0.501, "TS_PCT": 0.561, "PACE": 93.84, "PACE_PER40": 78.2, "POSS": 7824}, "ORL": {"TEAM_ID": 1610612753, "TEAM_NAME": "Orlando Magic", "GP": 82, "W": 52, "L": 30, "MIN": 3966.0, "OFF_RATING": 107.4, "DEF_RATING": 101.8, "NET_RATING": 5.6, "AST_PCT": 0.553, "AST_TO": 1.34, "AST_RATIO": 15.9, "OREB_PCT": 0.304, "DREB_PCT": 0.723, "REB_PCT": 0.518, "TM_TOV_PCT": 0.162, "EFG_PCT": 0.521, "TS_PCT": 0.554, "PACE": 91.55, "PACE_PER40": 76.29, "POSS": 7575}, "PHI": {"TEAM_ID": 1610612755, "TEAM_NAME": "Philadelphia 76ers", "GP": 82, "W": 41, "L": 41, "MIN": 3986.0, "OFF_RATING": 105.3, "DEF_RATING": 103.8, "NET_RATING": 1.5, "AST_PCT": 0.596, "AST_TO": 1.75, "AST_RATIO": 17.6, "OREB_PCT": 0.278, "DREB_PCT": 0.714, "REB_PCT": 0.497, "TM_TOV_PCT": 0.138, "EFG_PCT": 0.494, "TS_PCT": 0.535, "PACE": 92.78, "PACE_PER40": 77.32, "POSS": 7709}, "PHX": {"TEAM_ID": 1610612756, "TEAM_NAME": "Phoenix Suns", "GP": 82, "W": 40, "L": 42, "MIN": 4001.0, "OFF_RATING": 108.6, "DEF_RATING": 109.4, "NET_RATING": -0.8, "AST_PCT": 0.604, "AST_TO": 1.66, "AST_RATIO": 17.9, "OREB_PCT": 0.275, "DREB_PCT": 0.681, "REB_PCT": 0.48, "TM_TOV_PCT": 0.147, "EFG_PCT": 0.522, "TS_PCT": 0.559, "PACE": 95.18, "PACE_PER40": 79.32, "POSS": 7930}, "POR": {"TEAM_ID": 1610612757, "TEAM_NAME": "Portland Trail Blazers", "GP": 82, "W": 48, "L": 34, "MIN": 3961.0, "OFF_RATING": 107.3, "DEF_RATING": 105.7, "NET_RATING": 1.6, "AST_PCT": 0.588, "AST_TO": 1.62, "AST_RATIO": 16.9, "OREB_PCT": 0.331, "DREB_PCT": 0.682, "REB_PCT": 0.499, "TM_TOV_PCT": 0.145, "EFG_PCT": 0.486, "TS_PCT": 0.533, "PACE": 89.13, "PACE_PER40": 74.27, "POSS": 7359}, "SAC": {"TEAM_ID": 1610612758, "TEAM_NAME": "Sacramento Kings", "GP": 82, "W": 24, "L": 58, "MIN": 3971.0, "OFF_RATING": 102.9, "DEF_RATING": 108.4, "NET_RATING": -5.5, "AST_PCT": 0.534, "AST_TO": 1.27, "AST_RATIO": 15.4, "OREB_PCT": 0.334, "DREB_PCT": 0.702, "REB_PCT": 0.512, "TM_TOV_PCT": 0.167, "EFG_PCT": 0.48, "TS_PCT": 0.519, "PACE": 95.76, "PACE_PER40": 79.8, "POSS": 7923}, "SAS": {"TEAM_ID": 1610612759, "TEAM_NAME": "San Antonio Spurs", "GP": 82, "W": 61, "L": 21, "MIN": 3956.0, "OFF_RATING": 110.5, "DEF_RATING": 104.4, "NET_RATING": 6.1, "AST_PCT": 0.583, "AST_TO": 1.67, "AST_RATIO": 17.5, "OREB_PCT": 0.276, "DREB_PCT": 0.711, "REB_PCT": 0.5, "TM_TOV_PCT": 0.143, "EFG_PCT": 0.527, "TS_PCT": 0.567, "PACE": 93.34, "PACE_PER40": 77.78, "POSS": 7691}, "TOR": {"TEAM_ID": 1610612761, "TEAM_NAME": "Toronto Raptors", "GP": 82, "W": 22, "L": 60, "MIN": 3956.0, "OFF_RATING": 105.2, "DEF_RATING": 111.7, "NET_RATING": -6.5, "AST_PCT": 0.571, "AST_TO": 1.49, "AST_RATIO": 16.8, "OREB_PCT": 0.314, "DREB_PCT": 0.685, "REB_PCT": 0.495, "TM_TOV_PCT": 0.156, "EFG_PCT": 0.491, "TS_PCT": 0.533, "PACE": 93.78, "PACE_PER40": 78.15, "POSS": 7723}, "UTA": {"TEAM_ID": 1610612762, "TEAM_NAME": "Utah Jazz", "GP": 82, "W": 39, "L": 43, "MIN": 3976.0, "OFF_RATING": 107.0, "DEF_RATING": 108.8, "NET_RATING": -1.8, "AST_PCT": 0.627, "AST_TO": 1.63, "AST_RATIO": 18.0, "OREB_PCT": 0.314, "DREB_PCT": 0.679, "REB_PCT": 0.496, "TM_TOV_PCT": 0.154, "EFG_PCT": 0.498, "TS_PCT": 0.544, "PACE": 92.03, "PACE_PER40": 76.7, "POSS": 7619}, "WAS": {"TEAM_ID": 1610612764, "TEAM_NAME": "Washington Wizards", "GP": 82, "W": 23, "L": 59, "MIN": 3986.0, "OFF_RATING": 101.3, "DEF_RATING": 109.1, "NET_RATING": -7.8, "AST_PCT": 0.522, "AST_TO": 1.27, "AST_RATIO": 14.9, "OREB_PCT": 0.317, "DREB_PCT": 0.671, "REB_PCT": 0.488, "TM_TOV_PCT": 0.16, "EFG_PCT": 0.471, "TS_PCT": 0.513, "PACE": 94.76, "PACE_PER40": 78.97, "POSS": 7871}}}